    <annotation>
        <folder>VOC</folder>
        <filename>IMG-25252520-291.jpg</filename>
        <source>
            <database>Database</database>
        </source>
        <size>
            <width>800</width>
            <height>800</height>
            <depth>3</depth>
        </size>
        <segmented>0</segmented>
        <object>
        <name>Surface_pores</name>
        <pose>Unspecified</pose>
        <truncated>0</truncated>
        <difficult>0</difficult>
        <bndbox>
            <xmin>462</xmin>
            <ymin>320</ymin>
            <xmax>501</xmax>
            <ymax>360</ymax>
        </bndbox>
    </object>
        <object>
        <name>Surface_pores</name>
        <pose>Unspecified</pose>
        <truncated>0</truncated>
        <difficult>0</difficult>
        <bndbox>
            <xmin>466</xmin>
            <ymin>210</ymin>
            <xmax>523</xmax>
            <ymax>260</ymax>
        </bndbox>
    </object>
        <object>
        <name>Surface_pores</name>
        <pose>Unspecified</pose>
        <truncated>0</truncated>
        <difficult>0</difficult>
        <bndbox>
            <xmin>447</xmin>
            <ymin>549</ymin>
            <xmax>485</xmax>
            <ymax>577</ymax>
        </bndbox>
    </object>
        <object>
        <name>wrong_size</name>
        <pose>Unspecified</pose>
        <truncated>0</truncated>
        <difficult>0</difficult>
        <bndbox>
            <xmin>539</xmin>
            <ymin>692</ymin>
            <xmax>375</xmax>
            <ymax>25</ymax>
        </bndbox>
    </object>
        <object>
        <name>Weld</name>
        <pose>Unspecified</pose>
        <truncated>0</truncated>
        <difficult>0</difficult>
        <bndbox>
            <xmin>376</xmin>
            <ymin>74</ymin>
            <xmax>499</xmax>
            <ymax>150</ymax>
        </bndbox>
    </object>
        </annotation>
    