    <annotation>
        <folder>VOC</folder>
        <filename>IMG-2520-666.jpg</filename>
        <source>
            <database>Database</database>
        </source>
        <size>
            <width>800</width>
            <height>800</height>
            <depth>3</depth>
        </size>
        <segmented>0</segmented>
        <object>
        <name>good</name>
        <pose>Unspecified</pose>
        <truncated>0</truncated>
        <difficult>0</difficult>
        <bndbox>
            <xmin>468</xmin>
            <ymin>796</ymin>
            <xmax>201</xmax>
            <ymax>5</ymax>
        </bndbox>
    </object>
        <object>
        <name>Surface_pores</name>
        <pose>Unspecified</pose>
        <truncated>0</truncated>
        <difficult>0</difficult>
        <bndbox>
            <xmin>305</xmin>
            <ymin>479</ymin>
            <xmax>363</xmax>
            <ymax>532</ymax>
        </bndbox>
    </object>
        <object>
        <name>Surface_pores</name>
        <pose>Unspecified</pose>
        <truncated>0</truncated>
        <difficult>0</difficult>
        <bndbox>
            <xmin>268</xmin>
            <ymin>617</ymin>
            <xmax>305</xmax>
            <ymax>656</ymax>
        </bndbox>
    </object>
        </annotation>
    