    <annotation>
        <folder>VOC</folder>
        <filename>IMG-25252520-1027.jpg</filename>
        <source>
            <database>Database</database>
        </source>
        <size>
            <width>800</width>
            <height>800</height>
            <depth>3</depth>
        </size>
        <segmented>0</segmented>
        <object>
        <name>wrong_size</name>
        <pose>Unspecified</pose>
        <truncated>0</truncated>
        <difficult>0</difficult>
        <bndbox>
            <xmin>3</xmin>
            <ymin>345</ymin>
            <xmax>206</xmax>
            <ymax>612</ymax>
        </bndbox>
    </object>
        <object>
        <name>crater</name>
        <pose>Unspecified</pose>
        <truncated>0</truncated>
        <difficult>0</difficult>
        <bndbox>
            <xmin>233</xmin>
            <ymin>326</ymin>
            <xmax>799</xmax>
            <ymax>610</ymax>
        </bndbox>
    </object>
        <object>
        <name>Surface_pores</name>
        <pose>Unspecified</pose>
        <truncated>0</truncated>
        <difficult>0</difficult>
        <bndbox>
            <xmin>679</xmin>
            <ymin>439</ymin>
            <xmax>763</xmax>
            <ymax>530</ymax>
        </bndbox>
    </object>
        <object>
        <name>Surface_pores</name>
        <pose>Unspecified</pose>
        <truncated>0</truncated>
        <difficult>0</difficult>
        <bndbox>
            <xmin>272</xmin>
            <ymin>420</ymin>
            <xmax>335</xmax>
            <ymax>477</ymax>
        </bndbox>
    </object>
        </annotation>
    