    <annotation>
        <folder>VOC</folder>
        <filename>IMG-252520-916.jpg</filename>
        <source>
            <database>Database</database>
        </source>
        <size>
            <width>800</width>
            <height>800</height>
            <depth>3</depth>
        </size>
        <segmented>0</segmented>
        <object>
        <name>Weld</name>
        <pose>Unspecified</pose>
        <truncated>0</truncated>
        <difficult>0</difficult>
        <bndbox>
            <xmin>295</xmin>
            <ymin>1</ymin>
            <xmax>548</xmax>
            <ymax>321</ymax>
        </bndbox>
    </object>
        <object>
        <name>Not_fully_soldered</name>
        <pose>Unspecified</pose>
        <truncated>0</truncated>
        <difficult>0</difficult>
        <bndbox>
            <xmin>541</xmin>
            <ymin>661</ymin>
            <xmax>313</xmax>
            <ymax>318</ymax>
        </bndbox>
    </object>
        <object>
        <name>Weld</name>
        <pose>Unspecified</pose>
        <truncated>0</truncated>
        <difficult>0</difficult>
        <bndbox>
            <xmin>486</xmin>
            <ymin>775</ymin>
            <xmax>301</xmax>
            <ymax>655</ymax>
        </bndbox>
    </object>
        </annotation>
    